Metadata-Version: 2.1
Name: azureips
Version: 0.4.2
Summary: azureIPs: Gives unallocated Azure ips. 
Home-page: https://github.com/chowmean/azureips
Author: chowmean
Author-email: gaurav.dev.iiitm@gmail.com
License: Apache-2.0
Keywords: azureips,azure,network_interface_ips
Platform: UNKNOWN
Classifier: Programming Language :: Python
Classifier: Operating System :: OS Independent
Classifier: Intended Audience :: Developers
Classifier: Development Status :: 4 - Beta
Classifier: Environment :: Plugins
Classifier: Topic :: Software Development :: Libraries :: Python Modules
Classifier: License :: Other/Proprietary License
Classifier: Natural Language :: English
